{"type": "Feature", "id": 12514556, "properties": {"woe:id": 12514556, "woe:parent_id": 1140595, "woe:name": "Savannakhet Airport", "woe:placetype": 14, "woe:placetype_name": "Airport", "woe:lang": "ENG", "iso:country": "LA", "meta:provider": ["geoplanet:7.3.1", "geoplanet:7.3.2", "geoplanet:7.4.0", "geoplanet:7.4.1", "geoplanet:7.5.1", "geoplanet:7.5.2", "geoplanet:7.6.0", "geoplanet:7.8.1", "geoplanet:7.9.0", "geoplanet:7.10.0", "geoplanet:8.0.0", "woeplanet:8.0.0"], "meta:indexed": "2020-08-20T20:29:17.602909", "woe:alias_ENG_V": ["ZVK Airport", "ZVK"], "meta:updated": "2020-08-22T02:49:21.238477", "woe:hierarchy": {"continent": 24865671, "country": 23424872, "town": 0, "planet": 1, "county": 0, "suburb": 0, "state": 2346008, "region": 0, "localadmin": 0}, "woe:timezone_id": 28350863, "woe:hash": "w6fqpvmxxnew", "woe:centroid": [104.762497, 16.5536], "geom:latitude": 16.5536, "geom:longitude": 104.762497, "geom:hash": "w6fqpvmxxnew", "woe:latitude": 16.5536, "geom:centroid": [104.762497, 16.5536], "woe:longitude": 104.762497, "woe:repo": "woeplanet-airport-la"}, "geometry": {"coordinates": [104.762497, 16.5536], "type": "Point"}}