{"type": "Feature", "id": 12514555, "geometry": {"type": "Point", "coordinates": [104.065598, 20.4076]}, "properties": {"woe:id": 12514555, "woe:parent_id": 1140607, "woe:name": "Sam Neua Airport", "woe:placetype": 14, "woe:placetype_name": "Airport", "woe:lang": "ENG", "iso:country": "LA", "meta:provider": ["geoplanet:7.3.1", "geoplanet:7.3.2", "geoplanet:7.4.0", "geoplanet:7.4.1", "geoplanet:7.5.1", "geoplanet:7.5.2", "geoplanet:7.6.0", "geoplanet:7.8.1", "geoplanet:7.9.0", "geoplanet:7.10.0", "geoplanet:8.0.0", "woeplanet:8.0.0"], "meta:indexed": "2020-08-20T20:29:17.602054", "meta:updated": "2020-10-14T11:35:33.658446", "woe:hierarchy": {"continent": 24865671, "country": 23424872, "town": 0, "planet": 1, "county": 0, "suburb": 0, "state": 2346001, "region": 0, "localadmin": 0}, "woe:timezone_id": 28350863, "woe:hash": "w7dh0546bhq5", "woe:centroid": [104.065598, 20.4076], "geom:latitude": 20.4076, "geom:longitude": 104.065598, "geom:hash": "w7dh0546bhq5", "woe:latitude": 20.4076, "geom:centroid": [104.065598, 20.4076], "woe:longitude": 104.065598, "woe:repo": "woeplanet-airport-la", "geom:area": 0.0, "woe:scale": 19}}