{"type": "Feature", "id": 12514539, "geometry": {"type": "Point", "coordinates": [102.250603, 19.1989]}, "properties": {"woe:id": 12514539, "woe:parent_id": 1138803, "woe:name": "Ban Na Then Airport", "woe:placetype": 14, "woe:placetype_name": "Airport", "woe:lang": "ENG", "iso:country": "LA", "meta:provider": ["geoplanet:7.3.1", "geoplanet:7.3.2", "geoplanet:7.4.0", "geoplanet:7.4.1", "geoplanet:7.5.1", "geoplanet:7.5.2", "geoplanet:7.6.0", "geoplanet:7.8.1", "geoplanet:7.9.0", "geoplanet:7.10.0", "geoplanet:8.0.0", "woeplanet:8.0.0"], "meta:indexed": "2020-08-20T20:29:17.588022", "meta:updated": "2020-10-14T11:35:33.654259", "woe:hierarchy": {"continent": 24865671, "country": 23424872, "town": 0, "planet": 1, "county": 0, "suburb": 0, "state": 2346004, "region": 0, "localadmin": 0}, "woe:timezone_id": 28350863, "woe:hash": "w72tnz09ewre", "woe:centroid": [102.250603, 19.1989], "geom:latitude": 19.1989, "geom:longitude": 102.250603, "geom:hash": "w72tnz09ewre", "woe:latitude": 19.1989, "geom:centroid": [102.250603, 19.1989], "woe:longitude": 102.250603, "woe:repo": "woeplanet-airport-la", "geom:area": 0.0, "woe:scale": 19}}