{"type": "Feature", "id": 12514548, "properties": {"woe:id": 12514548, "woe:parent_id": 1139800, "woe:name": "Muang Phonsavan Airport", "woe:placetype": 14, "woe:placetype_name": "Airport", "woe:lang": "ENG", "iso:country": "LA", "meta:provider": ["geoplanet:7.3.1", "geoplanet:7.3.2", "geoplanet:7.4.0", "geoplanet:7.4.1", "geoplanet:7.5.1", "geoplanet:7.5.2", "geoplanet:7.6.0", "geoplanet:7.8.1", "geoplanet:7.9.0", "geoplanet:7.10.0", "geoplanet:8.0.0", "woeplanet:8.0.0"], "meta:indexed": "2020-08-20T20:29:17.595841", "meta:updated": "2020-08-22T02:49:21.235858", "woe:hierarchy": {"continent": 24865671, "country": 23424872, "town": 0, "planet": 1, "county": 0, "suburb": 0, "state": 2346011, "region": 0, "localadmin": 0}, "woe:timezone_id": 28350863, "woe:hash": "w73qsv9bvtvv", "woe:centroid": [103.2192, 19.454201], "geom:latitude": 19.454201, "geom:longitude": 103.2192, "geom:hash": "w73qsv9bvtvv", "woe:latitude": 19.454201, "geom:centroid": [103.2192, 19.454201], "woe:longitude": 103.2192, "woe:repo": "woeplanet-airport-la"}, "geometry": {"coordinates": [103.2192, 19.454201], "type": "Point"}}